Metadata-Version: 1.0
Name: neulprogrammist
Version: 0.0
Summary: Created for fun!
Home-page: UNKNOWN
Author: UNKNOWN
Author-email: abbaslutvaliyev@icloud.com
License: UNKNOWN
Platform: UNKNOWN
